setup.py
scyred/__init__.py
scyred.egg-info/PKG-INFO
scyred.egg-info/SOURCES.txt
scyred.egg-info/dependency_links.txt
scyred.egg-info/requires.txt
scyred.egg-info/top_level.txt