Metadata-Version: 1.0
Name: scyred
Version: 0.0.3
Summary: Library that joins scikit-learn with inspyred to create an easy-to-use parameter tuning
Home-page: https://github.com/caiocarneloz/scyred
Author: Caio Carneloz
Author-email: caiocarneloz@gmail.com
License: MIT License
Keywords: optimizer
Platform: UNKNOWN
